expandvars.py
expandvars-1.1.0.dist-info/METADATA
expandvars-1.1.0.dist-info/WHEEL
expandvars-1.1.0.dist-info/licenses/LICENSE
expandvars-1.1.0.dist-info/RECORD
