Metadata-Version: 2.4
Name: expandvars
Version: 1.1.0
Summary: Expand system variables Unix style
Project-URL: Homepage, https://github.com/sayanarijit/expandvars
Author-email: Arijit Basu <sayanarijit@gmail.com>
Maintainer-email: Arijit Basu <sayanarijit@gmail.com>
License: MIT License
License-File: LICENSE
Keywords: expand,system,variables
Classifier: Development Status :: 5 - Production/Stable
Classifier: Intended Audience :: Developers
Classifier: Intended Audience :: Information Technology
Classifier: Intended Audience :: Other Audience
Classifier: License :: OSI Approved :: MIT License
Classifier: Natural Language :: English
Classifier: Operating System :: MacOS
Classifier: Operating System :: Microsoft
Classifier: Operating System :: POSIX
Classifier: Operating System :: Unix
Classifier: Programming Language :: Python :: 3
Classifier: Topic :: Software Development
Classifier: Topic :: Utilities
Requires-Python: >=3.6.2
Provides-Extra: tests
Requires-Dist: black; extra == 'tests'
Requires-Dist: pytest; extra == 'tests'
Requires-Dist: pytest-cov; extra == 'tests'
Requires-Dist: tox; extra == 'tests'
